namari/__init__.py
namari/namari - Copy.py
namari/namari.py
namari/version.py
namari-1.1.9.dist-info/LICENSE
namari-1.1.9.dist-info/METADATA
namari-1.1.9.dist-info/WHEEL
namari-1.1.9.dist-info/top_level.txt
namari-1.1.9.dist-info/RECORD
