Metadata-Version: 2.1
Name: namari
Version: 1.1.9
Summary: Many-to-one keys-value pair relationship Python object manager.
Home-page: https://github.com/rmaniego/namari
Author: Rodney Maniego Jr.
Author-email: rod.maniego23@gmail.com
License: MIT
Download-URL: https://github.com/rmaniego/namari/archive/v1.0.tar.gz
Keywords: Dictionary,JSON,many-to-many,keys-value,multiple relationship
Platform: UNKNOWN
Classifier: Development Status :: 5 - Production/Stable
Classifier: Intended Audience :: Developers
Classifier: Topic :: Software Development :: Build Tools
Classifier: License :: OSI Approved :: MIT License
Classifier: Programming Language :: Python :: 3
Requires-Python: >=3.6
License-File: LICENSE
Requires-Dist: arkivist
